{
  "swagger": "2.0",
  "info": {
    "version": "1.0.0",
    "title": "REST API",
    "description": ""
  },
  "host": "localhost:3000",
  "basePath": "/",
  "schemes": [
    "http"
  ],
  "paths": {
    "/": {
      "get": {
        "description": "",
        "responses": {
          "200": {
            "description": "OK"
          }
        }
      }
    },
    "/autenticacao/login": {
      "post": {
        "summary": "Usuário tem acesso ao seu token",
        "description": "",
        "parameters": [
          {
            "name": "body",
            "in": "body",
            "schema": {
              "type": "object",
              "properties": {
                "email": {
                  "example": "any"
                },
                "senha": {
                  "example": "any"
                }
              }
            }
          }
        ],
        "responses": {
          "200": {
            "description": "OK"
          },
          "404": {
            "description": "Not Found"
          },
          "422": {
            "description": "Unprocessable Entity"
          },
          "500": {
            "description": "Internal Server Error"
          }
        }
      }
    },
    "/usuario/{id}": {
      "get": {
        "summary": "Lista usuários por ID",
        "description": "",
        "parameters": [
          {
            "name": "id",
            "in": "path",
            "required": true,
            "type": "string"
          }
        ],
        "responses": {
          "200": {
            "description": "OK"
          },
          "400": {
            "description": "Bad Request"
          }
        }
      },
      "put": {
        "summary": "Atualiza usuário",
        "description": "",
        "parameters": [
          {
            "name": "id",
            "in": "path",
            "required": true,
            "type": "string"
          },
          {
            "name": "body",
            "in": "body",
            "schema": {
              "type": "object",
              "properties": {
                "nome": {
                  "example": "any"
                },
                "biografia": {
                  "example": "any"
                }
              }
            }
          }
        ],
        "responses": {
          "200": {
            "description": "OK"
          },
          "403": {
            "description": "Forbidden"
          },
          "404": {
            "description": "Not Found"
          },
          "500": {
            "description": "Internal Server Error"
          }
        }
      },
      "delete": {
        "summary": "Remove usuário",
        "description": "",
        "parameters": [
          {
            "name": "id",
            "in": "path",
            "required": true,
            "type": "string"
          }
        ],
        "responses": {
          "200": {
            "description": "OK"
          },
          "400": {
            "description": "Bad Request"
          },
          "403": {
            "description": "Forbidden"
          },
          "404": {
            "description": "Not Found"
          }
        }
      }
    },
    "/usuario": {
      "get": {
        "summary": "Lista usuários",
        "description": "",
        "responses": {
          "200": {
            "description": "OK"
          }
        }
      }
    },
    "/usuario/registro": {
      "post": {
        "summary": "Cadastra usuário",
        "description": "",
        "parameters": [
          {
            "name": "body",
            "in": "body",
            "schema": {
              "type": "object",
              "properties": {
                "nome": {
                  "example": "any"
                },
                "email": {
                  "example": "any"
                },
                "senha": {
                  "example": "any"
                },
                "biografia": {
                  "example": "any"
                }
              }
            }
          }
        ],
        "responses": {
          "201": {
            "description": "Created"
          },
          "422": {
            "description": "Unprocessable Entity"
          },
          "500": {
            "description": "Internal Server Error"
          }
        }
      }
    },
    "/publicao/{id}": {
      "get": {
        "summary": "Lista publicações por ID",
        "description": "",
        "parameters": [
          {
            "name": "id",
            "in": "path",
            "required": true,
            "type": "string"
          }
        ],
        "responses": {
          "default": {
            "description": ""
          }
        }
      }
    },
    "/publicacao": {
      "get": {
        "summary": "Lista publicações",
        "description": "",
        "parameters": [
          {
            "name": "titulo",
            "in": "query",
            "type": "string"
          },
          {
            "name": "categoria",
            "in": "query",
            "type": "string"
          },
          {
            "name": "dataCriacao",
            "in": "query",
            "type": "string"
          }
        ],
        "responses": {
          "default": {
            "description": ""
          }
        }
      }
    },
    "/publicacao/registro": {
      "post": {
        "summary": "Cadastra publicação",
        "description": "",
        "responses": {
          "201": {
            "description": "Created"
          },
          "500": {
            "description": "Internal Server Error"
          }
        }
      }
    },
    "/publicacao/{id}": {
      "put": {
        "summary": "Atualiza publicação",
        "description": "",
        "parameters": [
          {
            "name": "id",
            "in": "path",
            "required": true,
            "type": "string"
          }
        ],
        "responses": {
          "200": {
            "description": "OK"
          },
          "403": {
            "description": "Forbidden"
          },
          "404": {
            "description": "Not Found"
          },
          "500": {
            "description": "Internal Server Error"
          }
        }
      },
      "delete": {
        "summary": "Remove publicação",
        "description": "",
        "parameters": [
          {
            "name": "id",
            "in": "path",
            "required": true,
            "type": "string"
          }
        ],
        "responses": {
          "200": {
            "description": "OK"
          },
          "400": {
            "description": "Bad Request"
          },
          "403": {
            "description": "Forbidden"
          },
          "404": {
            "description": "Not Found"
          }
        }
      }
    },
    "/admin/criar-admin-padrao": {
      "post": {
        "description": "",
        "responses": {
          "200": {
            "description": "OK"
          },
          "500": {
            "description": "Internal Server Error"
          }
        }
      }
    },
    "/admin/registro": {
      "post": {
        "summary": "Cadastra admin",
        "description": "",
        "parameters": [
          {
            "name": "body",
            "in": "body",
            "schema": {
              "type": "object",
              "properties": {
                "nome": {
                  "example": "any"
                },
                "email": {
                  "example": "any"
                },
                "senha": {
                  "example": "any"
                },
                "biografia": {
                  "example": "any"
                }
              }
            }
          }
        ],
        "responses": {
          "201": {
            "description": "Created"
          },
          "403": {
            "description": "Forbidden"
          },
          "422": {
            "description": "Unprocessable Entity"
          },
          "500": {
            "description": "Internal Server Error"
          }
        }
      }
    },
    "/admin/exluir/{id}": {
      "delete": {
        "summary": "Admin remove usuário",
        "description": "",
        "parameters": [
          {
            "name": "id",
            "in": "path",
            "required": true,
            "type": "string"
          }
        ],
        "responses": {
          "200": {
            "description": "OK"
          },
          "403": {
            "description": "Forbidden"
          },
          "404": {
            "description": "Not Found"
          },
          "500": {
            "description": "Internal Server Error"
          }
        }
      }
    }
  }
}